{
    "$schema": "https://schema.management.azure.com/schemas/2015-01-01/deploymentTemplate.json#",
    "contentVersion": "1.0.0.0",

    "parameters": {
        "apiVersion": { "type": "string", "defaultValue":"2016-02-01",     "metadata": { "description": "Common API"                   } },
        "vmName":     { "type": "string",                                  "metadata": { "description": "Name of the Virtual Machine." } }
    },

    "resources": [
        {
            "name": "[concat(parameters('vmName'),'/', 'IIS')]",
            "type": "Microsoft.Compute/virtualMachines/extensions",
            "location": "[resourceGroup().location]",
            "apiVersion": "2015-06-15",

            "properties": {
                "publisher": "Microsoft.Powershell",
                "type": "DSC",
                "typeHandlerVersion": "2.18",
                "settings": { "configuration": {"url": "https://azureclisa.blob.core.windows.net/dsc/dscWeb.zip", "script": "InstallWebComponents.ps1", "function": "DemoIIS" } },
                "protectedSettings": null
            }
        }
    ]
}
